cbv_tracker/__init__.py
cbv_tracker/django_cbv_tracker.py
cbv_tracker-0.0.5.dist-info/METADATA
cbv_tracker-0.0.5.dist-info/WHEEL
cbv_tracker-0.0.5.dist-info/top_level.txt
cbv_tracker-0.0.5.dist-info/RECORD
